<?xml version="1.0"?>
<enunciate label="gentics.kitchenoffice" xmlns:xsi="http://www.w3.org/2001/XMLSchema-instance" xsi:noNamespaceSchemaLocation="http://enunciate.codehaus.org/schemas/enunciate-1.25.xsd">
   <services>
         <rest defaultRestSubcontext="/kitchenoffice-restapi-webapp/rest"/>
   </services>

   <webapp disable="true"/>
   <modules>
      <!-- Docs -->
      <docs splashPackage="com.gentics.kitchenoffice.rest" title="Gentics Kitchen Office REST API"
        copyright="Gentics Software GmbH" includeExampleXml="false" includeExampleJson="true" css="my.css"/>
      <c disabled="true"/>
      <csharp disabled="true"/>
      <obj-c disabled="true"/>
      <java-client disabled="true"/>
      <jaxws-client disabled="true"/>
   </modules>
</enunciate>
